MANIFEST.in
setup.py
pymetfrag/MetFrag2.3-CL.jar
pymetfrag/__init__.py
pymetfrag/metfrag23.exe
pymetfrag/metfrag23.l4j.ini
pymetfrag/parameter_file_template.txt
pymetfrag/pymetfrag.py
pymetfrag.egg-info/PKG-INFO
pymetfrag.egg-info/SOURCES.txt
pymetfrag.egg-info/dependency_links.txt
pymetfrag.egg-info/entry_points.txt
pymetfrag.egg-info/requires.txt
pymetfrag.egg-info/top_level.txt