Metadata-Version: 1.0
Name: pymetfrag
Version: 0.5.1
Summary: Python wrapper of metfrag 2.3 for ms/ms based identification of LCMS data
Home-page: http://sis.id.ethz.ch
Author: Uwe Schmitt
Author-email: uwe.schmitt@id.ethz.ch
License: http://opensource.org/licenses/LGPL-2.1
Platform: UNKNOWN
